transcoder/translate.py
transcoder/XLM/preprocess.py
transcoder/XLM/train.py
transcoder/XLM/src/__init__.py
transcoder/XLM/src/logger.py
transcoder/XLM/src/optim.py
transcoder/XLM/src/slurm.py
transcoder/XLM/src/trainer.py
transcoder/XLM/src/utils.py
transcoder/XLM/src/data/__init__.py
transcoder/XLM/src/data/dataset.py
transcoder/XLM/src/data/dictionary.py
transcoder/XLM/src/data/loader.py
transcoder/XLM/src/evaluation/__init__.py
transcoder/XLM/src/evaluation/evaluator.py
transcoder/XLM/src/model/__init__.py
transcoder/XLM/src/model/embedder.py
transcoder/XLM/src/model/pretrain.py
transcoder/XLM/src/model/transformer.py
transcoder/preprocessing/__init__.py
transcoder/preprocessing/detokenize.py
transcoder/preprocessing/preprocess.py
transcoder/preprocessing/test_preprocess.py
transcoder/preprocessing/src/__init__.py
transcoder/preprocessing/src/code_tokenizer.py
transcoder/preprocessing/src/dataset.py
transcoder/preprocessing/src/javalang_tokenizer.py
transcoder/preprocessing/src/test_tokenize_cpp.py
transcoder/preprocessing/src/test_tokenize_java.py
transcoder/preprocessing/src/test_tokenize_python.py
transcoder/preprocessing/src/timeout.py
transcoder/preprocessing/src/utils.py
transcode-1.2.0.dist-info/LICENSE
transcode-1.2.0.dist-info/METADATA
transcode-1.2.0.dist-info/WHEEL
transcode-1.2.0.dist-info/entry_points.txt
transcode-1.2.0.dist-info/top_level.txt
transcode-1.2.0.dist-info/RECORD
