Metadata-Version: 2.1
Name: transcode
Version: 1.2.0
Summary: Packing transcoder model
Author-email: Ahmed Heakl <ahmed.heakl@ejust.edu.eg>
Project-URL: repository, https://github.com/ahmedheakl/transcoder-package
Keywords: transcoder,XLM,natural language,facebook,META,pytorch
Classifier: License :: OSI Approved :: MIT License
Classifier: Programming Language :: Python
Classifier: Programming Language :: Python :: 3
Requires-Python: >=3.7
License-File: LICENSE
Requires-Dist: torch
Requires-Dist: numpy
Requires-Dist: fastBPE
Requires-Dist: apex
Requires-Dist: libclang ==10.0.1
Requires-Dist: submitit
Requires-Dist: six
Requires-Dist: sacrebleu ==1.2.11
Requires-Dist: googledrivedownloader
Provides-Extra: build
Requires-Dist: build ; extra == 'build'
Requires-Dist: twine ; extra == 'build'
Provides-Extra: dev
Requires-Dist: black ; extra == 'dev'
Requires-Dist: bumpver ; extra == 'dev'
